{"_ts":[1483252383,1483339301,1483426236],"_r":{"breakdown":{"html":{"bytes":[15233,15233,15233],"requests":[1,1,1]},"js":{"bytes":[75638,75640,75640],"requests":[2,2,2]},"css":{"bytes":[40966,40966,40966],"requests":[2,2,2]},"image":{"bytes":[222711,222711,222711],"requests":[9,9,9]},"flash":{"bytes":[0,0,0],"requests":[0,0,0]},"font":{"bytes":[297124,297175,297175],"requests":[11,11,11]},"other":{"bytes":[0,0,0],"requests":[0,0,0]}},"date":[1483252383,1483339301,1483426236],"domElements":[714,714,714],"domInteractive":[1199,1375,1428],"firstPaint":[1479,1358,1414],"fullyLoaded":[5473,4346,6217],"id":["170101_6R_7K6","170102_FR_8S4","170103_A6_A2K"],"loadTime":[4352,3515,4862],"render":[1806,1516,1795],"SpeedIndex":[3072,2610,3275],"TTFB":[916,910,907],"videoFrames":[[{"_t":0,"_vc":0},{"_t":1800,"_vc":40},{"_t":2000,"_vc":44},{"_t":2300,"_vc":44},{"_t":2700,"_vc":61},{"_t":2900,"_vc":61},{"_t":3100,"_vc":74},{"_t":3300,"_vc":74},{"_t":4600,"_vc":74},{"_t":5300,"_vc":78},{"_t":5500,"_vc":94},{"_t":5700,"_vc":100}],[{"_t":0,"_vc":0},{"_t":1500,"_vc":40},{"_t":1700,"_vc":40},{"_t":1800,"_vc":44},{"_t":2000,"_vc":43},{"_t":2500,"_vc":50},{"_t":2600,"_vc":61},{"_t":2900,"_vc":74},{"_t":3000,"_vc":74},{"_t":3100,"_vc":74},{"_t":3600,"_vc":74},{"_t":4300,"_vc":91},{"_t":4400,"_vc":99},{"_t":4600,"_vc":100}],[{"_t":0,"_vc":0},{"_t":1800,"_vc":44},{"_t":2300,"_vc":44},{"_t":2800,"_vc":61},{"_t":3000,"_vc":74},{"_t":5100,"_vc":74},{"_t":6100,"_vc":82},{"_t":6300,"_vc":91},{"_t":6500,"_vc":97},{"_t":6700,"_vc":100}]],"visualComplete":[5697,4598,6688]}}